Metadata-Version: 2.1
Name: zzfgeodemo
Version: 0.0.1
Summary: A python package for interactive mapping
Home-page: https://github.com/giszzf/zzfgeodemo
Author: Zhifan Zhang
Author-email: 2692219488@qq.com
License: MIT license
Keywords: zzfgeodemo
Classifier: Intended Audience :: Developers
Classifier: License :: OSI Approved :: MIT License
Classifier: Natural Language :: English
Classifier: Programming Language :: Python :: 3
Classifier: Programming Language :: Python :: 3.8
Classifier: Programming Language :: Python :: 3.9
Classifier: Programming Language :: Python :: 3.10
Classifier: Programming Language :: Python :: 3.11
Requires-Python: >=3.8
License-File: LICENSE
